azure/iot/hub/__init__.py
azure/iot/hub/auth.py
azure/iot/hub/connection_string.py
azure/iot/hub/constant.py
azure/iot/hub/digital_twin_client.py
azure/iot/hub/iothub_amqp_client.py
azure/iot/hub/iothub_configuration_manager.py
azure/iot/hub/iothub_http_runtime_manager.py
azure/iot/hub/iothub_job_manager.py
azure/iot/hub/iothub_registry_manager.py
azure/iot/hub/models.py
azure/iot/hub/sastoken.py
azure/iot/hub/protocol/__init__.py
azure/iot/hub/protocol/iot_hub_gateway_service_ap_is.py
azure/iot/hub/protocol/version.py
azure/iot/hub/protocol/models/__init__.py
azure/iot/hub/protocol/models/authentication_mechanism.py
azure/iot/hub/protocol/models/authentication_mechanism_py3.py
azure/iot/hub/protocol/models/bulk_registry_operation_result.py
azure/iot/hub/protocol/models/bulk_registry_operation_result_py3.py
azure/iot/hub/protocol/models/cloud_to_device_method.py
azure/iot/hub/protocol/models/cloud_to_device_method_py3.py
azure/iot/hub/protocol/models/cloud_to_device_method_result.py
azure/iot/hub/protocol/models/cloud_to_device_method_result_py3.py
azure/iot/hub/protocol/models/configuration.py
azure/iot/hub/protocol/models/configuration_content.py
azure/iot/hub/protocol/models/configuration_content_py3.py
azure/iot/hub/protocol/models/configuration_metrics.py
azure/iot/hub/protocol/models/configuration_metrics_py3.py
azure/iot/hub/protocol/models/configuration_py3.py
azure/iot/hub/protocol/models/configuration_queries_test_input.py
azure/iot/hub/protocol/models/configuration_queries_test_input_py3.py
azure/iot/hub/protocol/models/configuration_queries_test_response.py
azure/iot/hub/protocol/models/configuration_queries_test_response_py3.py
azure/iot/hub/protocol/models/device.py
azure/iot/hub/protocol/models/device_capabilities.py
azure/iot/hub/protocol/models/device_capabilities_py3.py
azure/iot/hub/protocol/models/device_job_statistics.py
azure/iot/hub/protocol/models/device_job_statistics_py3.py
azure/iot/hub/protocol/models/device_py3.py
azure_iot_hub-2.6.0.dist-info/METADATA
azure_iot_hub-2.6.0.dist-info/WHEEL
azure_iot_hub-2.6.0.dist-info/top_level.txt
azure_iot_hub-2.6.0.dist-info/RECORD
